<?xml version="1.0" encoding="windows-1252" ?>
<!DOCTYPE ViewLink SYSTEM "jbo_03_01.dtd">
<!---->
<ViewLink
  xmlns="http://xmlns.oracle.com/bc4j"
  Name="FkVoucherDetVoucherSeqLink"
  Version="12.1.3.10.47"
  InheritPersonalization="merge"
  EntityAssociation="erpsolgls.erpsolglsmodel.erpsolglseo.FkVoucherDetVoucherSeqAssoc">
  <ViewLinkDefEnd
    Name="VoucherView"
    Cardinality="1"
    Source="true"
    Owner="erpsolgls.erpsolglsmodel.erpsolglsvo.VoucherView">
    <DesignTime>
      <Attr Name="_finderName" Value="VoucherView"/>
      <Attr Name="_isUpdateable" Value="true"/>
    </DesignTime>
    <AttrArray Name="Attributes">
      <Item Value="erpsolgls.erpsolglsmodel.erpsolglsvo.VoucherView.Voucherseq"/>
    </AttrArray>
  </ViewLinkDefEnd>
  <ViewLinkDefEnd
    Name="VoucherDetView"
    Cardinality="-1"
    Owner="erpsolgls.erpsolglsmodel.erpsolglsvo.VoucherDetView">
    <DesignTime>
      <Attr Name="_finderName" Value="VoucherDetView"/>
      <Attr Name="_isUpdateable" Value="true"/>
    </DesignTime>
    <AttrArray Name="Attributes">
      <Item Value="erpsolgls.erpsolglsmodel.erpsolglsvo.VoucherDetView.Voucherseq"/>
    </AttrArray>
  </ViewLinkDefEnd>
</ViewLink>
